quicktranslate.py
quicktranslate-1.1.1.dist-info/METADATA
quicktranslate-1.1.1.dist-info/WHEEL
quicktranslate-1.1.1.dist-info/entry_points.txt
quicktranslate-1.1.1.dist-info/top_level.txt
quicktranslate-1.1.1.dist-info/RECORD
